anya_dash/AnyaAffix.py
anya_dash/AnyaButton.py
anya_dash/AnyaCard.py
anya_dash/AnyaCheckbox.py
anya_dash/AnyaCheckboxGroup.py
anya_dash/AnyaCol.py
anya_dash/AnyaCollapse.py
anya_dash/AnyaContent.py
anya_dash/AnyaDash.py
anya_dash/AnyaDateRangePicker.py
anya_dash/AnyaDivider.py
anya_dash/AnyaExecuteJs.py
anya_dash/AnyaFooter.py
anya_dash/AnyaHeader.py
anya_dash/AnyaIcon.py
anya_dash/AnyaInput.py
anya_dash/AnyaInputNumber.py
anya_dash/AnyaLayout.py
anya_dash/AnyaMenu.py
anya_dash/AnyaModal.py
anya_dash/AnyaParagraph.py
anya_dash/AnyaRadioGroup.py
anya_dash/AnyaRow.py
anya_dash/AnyaSelect.py
anya_dash/AnyaSider.py
anya_dash/AnyaSlider.py
anya_dash/AnyaSpace.py
anya_dash/AnyaSwitch.py
anya_dash/AnyaTable.py
anya_dash/AnyaTable2.py
anya_dash/AnyaTabs.py
anya_dash/AnyaTag.py
anya_dash/AnyaText.py
anya_dash/AnyaTheme.py
anya_dash/AnyaTitle.py
anya_dash/__init__.py
anya_dash/_imports_.py
anya_dash/anya_dash.min.js
anya_dash/anya_dash.min.js.map
anya_dash/metadata.json
anya_dash/package-info.json
anya_dash-0.1.0.dist-info/LICENSE
anya_dash-0.1.0.dist-info/METADATA
anya_dash-0.1.0.dist-info/WHEEL
anya_dash-0.1.0.dist-info/top_level.txt
anya_dash-0.1.0.dist-info/RECORD
